{
  "opendb_id": "0609296b-f452-49a6-a662-6b7c80d118e4",
  "metadata": {
    "name": "SK Hynix Platinum P41 500GB M.2-2280 PCIe 4.0 NVMe SSD",
    "manufacturer": "SK Hynix",
    "part_numbers": [
      "SHPP41-500GM-2"
    ],
    "series": "Platinum",
    "variant": "500GB"
  },
  "capacity": 500,
  "type": "SSD",
  "form_factor": "M.2-2280",
  "interface": "M.2 PCIe 4.0 X4",
  "nvme": true,
  "general_product_information": {
    "newegg_sku": "0D9-00BB-00046",
    "walmart_sku": 799637136
  }
}