{
  "opendb_id": "72830735-716f-42a4-abce-ea7eafe9236f",
  "metadata": {
    "name": "PNY CS900 240GB 2.5\" SSD",
    "manufacturer": "PNY",
    "part_numbers": [
      "SSD7CS900-240-RB                                                    SSD7CS900-240-PB"
    ],
    "series": "CS900",
    "variant": "240GB"
  },
  "capacity": 240,
  "type": "SSD",
  "form_factor": "2.5\"",
  "interface": "SATA 6.0 Gb/s",
  "nvme": false,
  "general_product_information": {
    "newegg_sku": "9SIA17PJDK3999",
    "bestbuy_sku": 5900261,
    "walmart_sku": 850589596,
    "adorama_sku": "PNSSD900240"
  }
}