{
  "opendb_id": "86124511-ebad-43c6-89ed-01d95d1135ce",
  "metadata": {
    "name": "SanDisk SSD PLUS 480 GB 2.5\"",
    "manufacturer": "SanDisk",
    "part_numbers": [
      "SDSSDA-480G-G26"
    ],
    "series": "SSD",
    "variant": "480GB"
  },
  "capacity": 480,
  "type": "SSD",
  "form_factor": "2.5\"",
  "interface": "SATA 6.0 Gb/s",
  "nvme": false,
  "general_product_information": {
    "newegg_sku": "N82E16820173152",
    "walmart_sku": 54277070,
    "adorama_sku": "IDSDSSA48G26"
  }
}