{
  "opendb_id": "da074617-999d-43d9-9896-c64e85f0279d",
  "metadata": {
    "name": "Seagate FireCuda 520 500GB M.2-2280 PCIe 4.0 X4 NVMe",
    "manufacturer": "Seagate",
    "part_numbers": [
      "ZP500GM3A002"
    ],
    "series": "FireCuda",
    "variant": "500GB"
  },
  "capacity": 500,
  "type": "SSD",
  "form_factor": "M.2-2280",
  "interface": "M.2 PCIe 4.0 X4",
  "nvme": true,
  "general_product_information": {
    "newegg_sku": "9SIBTK0K928033",
    "bestbuy_sku": 6440211,
    "walmart_sku": 985330397
  }
}