{
  "opendb_id": "e44983d5-dfdc-4fd5-9b4e-9e4cdcddbf07",
  "metadata": {
    "name": "Crucial T705 W/Heatsink 4 TB M.2-2280 PCIe 5.0 X4 NVME",
    "manufacturer": "Crucial",
    "part_numbers": [
      "CT4000T705SSD5"
    ],
    "series": "T705",
    "variant": "4000GB"
  },
  "capacity": 4000,
  "type": "SSD",
  "form_factor": "M.2-2280",
  "interface": "M.2 PCIe 5.0 X4",
  "nvme": true,
  "general_product_information": {
    "newegg_sku": "N82E16820156402",
    "walmart_sku": 5324582195
  }
}