{
  "opendb_id": "b014ca3a-4c61-4beb-be7a-d300ab9e903a",
  "power_connectors": {
    "pcie_6_pin": 0,
    "pcie_8_pin": 2,
    "pcie_12VHPWR": 0,
    "pcie_12V_2x6": 0
  },
  "metadata": {
    "name": "Asus RX6800-16G Radeon RX 6800 16 GB",
    "manufacturer": "Asus",
    "part_numbers": [
      "RX6800-16G"
    ],
    "series": "Radeon RX 6800",
    "variant": "Asus"
  },
  "chipset_manufacturer": "Radeon",
  "chipset": "Radeon RX 6800",
  "memory": 16,
  "memory_type": "GDDR6",
  "core_base_clock": 1700,
  "core_boost_clock": 2105,
  "effective_memory_clock": 16000,
  "memory_bus": 0,
  "interface": "PCIe x16",
  "color": "Blue / Silver",
  "frame_sync": "FreeSync",
  "length": 267,
  "tdp": 250,
  "case_expansion_slot_width": 2,
  "total_slot_width": 2,
  "cooling": "3 Fans",
  "video_outputs": {
    "hdmi_2_1": 0,
    "hdmi_2_0": 1,
    "displayport_2_1": 0,
    "displayport_2_1a": 0,
    "displayport_1_4a": 2,
    "dvi_d": 0,
    "vga": 0,
    "_id": "67e89c7611815510c7c791e0"
  },
  "general_product_information": {}
}