{
  "opendb_id": "4ab4be6e-1cb6-4d05-a6b9-5d3790ad0ffa",
  "connectors": {
    "atx_24_pin": 1,
    "eps_8_pin": 1,
    "pcie_12vhpwr": 0,
    "pcie_6_plus_2_pin": 0,
    "sata": 3,
    "molex_4_pin": 3,
    "floppy_4_pin": 0
  },
  "metadata": {
    "name": "Sparkle SPI460PFB2-MC2 460 W 80+ Certified ATX",
    "manufacturer": "Sparkle",
    "part_numbers": [
      "SPI460PFB2-MC2"
    ],
    "series": "SPI460PFB2-MC2",
    "variant": "460W 80+"
  },
  "wattage": 460,
  "form_factor": "ATX",
  "efficiency_rating": "80+",
  "modular": "Non-Modular",
  "color": [],
  "length": 139,
  "fanless": false,
  "general_product_information": {}
}