{
  "opendb_id": "63690434-ce8b-416b-9958-d6f947f543a8",
  "connectors": {
    "atx_24_pin": 1,
    "eps_8_pin": 0,
    "pcie_12vhpwr": 0,
    "pcie_6_plus_2_pin": 0,
    "sata": 4,
    "molex_4_pin": 0,
    "floppy_4_pin": 0
  },
  "metadata": {
    "name": "ARESGAME AGV 500 W 80+ Bronze Certified ATX",
    "manufacturer": "ARESGAME",
    "part_numbers": [
      "AGV500"
    ],
    "series": "AGV",
    "variant": "500W Bronze"
  },
  "wattage": 500,
  "form_factor": "ATX",
  "efficiency_rating": "80+ Bronze",
  "modular": "Non-Modular",
  "color": "Black",
  "length": 140,
  "fanless": false,
  "general_product_information": {}
}