{
  "opendb_id": "869b5b8b-5f13-4f05-85a2-d04b3b042a08",
  "connectors": {
    "atx_24_pin": 1,
    "eps_8_pin": 2,
    "pcie_12vhpwr": 1,
    "pcie_6_plus_2_pin": 3,
    "sata": 12,
    "molex_4_pin": 3,
    "floppy_4_pin": 0
  },
  "metadata": {
    "name": "PC Cooler YS1200 1200 W 80+ Gold Certified Fully Modular ATX",
    "manufacturer": "PC Cooler",
    "part_numbers": [
      "P5-YS1200-G1FFBK1-US"
    ],
    "series": "YS1200",
    "variant": "1200W Gold"
  },
  "wattage": 1200,
  "form_factor": "ATX",
  "efficiency_rating": "80+ Gold",
  "modular": "Full",
  "color": "Black",
  "length": 160,
  "fanless": false,
  "general_product_information": {}
}