{
  "opendb_id": "ca157795-11c7-488c-ba9a-0e150c12122e",
  "connectors": {
    "atx_24_pin": 1,
    "eps_8_pin": 2,
    "pcie_12vhpwr": 0,
    "pcie_6_plus_2_pin": 4,
    "sata": 6,
    "molex_4_pin": 4,
    "floppy_4_pin": 0
  },
  "metadata": {
    "name": "Apex AG-M 650W Fully Modular 80+ Gold Certified ATX",
    "manufacturer": "Apex",
    "part_numbers": [
      "AG-650M"
    ],
    "series": "AG-M",
    "variant": "650W Gold"
  },
  "wattage": 650,
  "form_factor": "ATX",
  "efficiency_rating": "80+ Gold",
  "modular": "Full",
  "color": [
    "BLACK"
  ],
  "length": 160,
  "fanless": false,
  "general_product_information": {}
}