{
  "opendb_id": "d6b75426-364e-454e-b193-35e083d46a5b",
  "connectors": {
    "atx_24_pin": 1,
    "eps_8_pin": 2,
    "pcie_12vhpwr": 2,
    "pcie_6_plus_2_pin": 8,
    "sata": 20,
    "molex_4_pin": 6,
    "floppy_4_pin": 0
  },
  "metadata": {
    "name": "LC-Power LC1200P V3.0 1200W Fully Modular 80+ Platinum",
    "manufacturer": "LC-Power",
    "part_numbers": [
      "LC1200P V3.0"
    ],
    "series": "LC1200P",
    "variant": "1200W Platinum"
  },
  "wattage": 1200,
  "form_factor": "ATX",
  "efficiency_rating": "80+ Platinum",
  "modular": "Full",
  "color": [
    "BLACK"
  ],
  "length": 180,
  "fanless": false,
  "general_product_information": {}
}