{
  "opendb_id": "da8c12d8-0f46-4a11-8e04-bbbce24e6413",
  "connectors": {
    "atx_24_pin": 1,
    "eps_8_pin": 1,
    "pcie_12vhpwr": 0,
    "pcie_6_plus_2_pin": 1,
    "sata": 4,
    "molex_4_pin": 2,
    "floppy_4_pin": 0
  },
  "metadata": {
    "name": "Kuroutoshikou KRPW-L5-500W/80+ 500 W 80+ Certified ATX",
    "manufacturer": "Kuroutoshikou",
    "part_numbers": [
      "KRPW-L5-500W",
      "80+"
    ],
    "series": "KRPW-L5-500W/80+",
    "variant": "500W 80+"
  },
  "wattage": 500,
  "form_factor": "ATX",
  "efficiency_rating": "80+",
  "modular": "Non-Modular",
  "color": "",
  "length": 140,
  "fanless": false,
  "general_product_information": {}
}