{
  "opendb_id": "13890e42-7d80-43db-9ef8-4b65b9c13276",
  "metadata": {
    "name": "Montech Sky 3 White",
    "manufacturer": "MONTECH",
    "series": "Sky 3",
    "variant": "White",
    "releaseYear": 2026,
    "manufacturer_color": "White",
    "part_numbers": []
  },
  "form_factor": "ATX Mid Tower",
  "supported_motherboard_form_factors": ["Mini-ITX", "Micro ATX", "ATX"],
  "color": ["WHITE"],
  "side_panel": "Tempered Glass",
  "has_transparent_side_panel": true,
  "supports_rear_connecting_motherboard": true,
  "supported_power_supply_form_factors": [],
  "front_usb_ports": [],
  "general_product_information": {}
}
