{
  "opendb_id": "3ce0b352-fac1-4439-878a-9b276d198ee8",
  "metadata": {
    "name": "Silverstone GD10B HTPC",
    "manufacturer": "Silverstone",
    "part_numbers": [
      "SST-GD10B"
    ],
    "series": "GD10B",
    "variant": ""
  },
  "form_factor": "HTPC",
  "color": [
    "BLACK"
  ],
  "power_supply": "None",
  "side_panel": "None",
  "has_transparent_side_panel": false,
  "front_panel_usb": "USB 3.2 Gen 1 Type-A",
  "max_video_card_length": 309,
  "max_cpu_cooler_height": null,
  "internal_3_5_bays": 2,
  "internal_2_5_bays": 1,
  "expansion_slots": 7,
  "dimensions": "362 x 442 x 171",
  "volume": 27.361,
  "weight": null,
  "general_product_information": {}
}