{
  "opendb_id": "f38f2794-6b90-4f01-ab9c-3d3940e6ef7d",
  "metadata": {
    "name": "Jonsbo Jonsplus Z20 MicroATX Desktop",
    "manufacturer": "Jonsbo",
    "part_numbers": [
      "Z20 Orange",
      "Black"
    ],
    "series": "Jonsplus",
    "variant": ""
  },
  "form_factor": "Micro ATX Desktop",
  "color": "Orange / Black",
  "power_supply": "None",
  "side_panel": "Tempered Glass",
  "has_transparent_side_panel": true,
  "front_panel_usb": "USB 3.2 Gen 2 Type-C                                                    USB 3.2 Gen 1 Type-A",
  "max_video_card_length": 363,
  "max_cpu_cooler_height": null,
  "internal_3_5_bays": 1,
  "internal_2_5_bays": 2,
  "expansion_slots": 4,
  "dimensions": "382 x 198 x 335",
  "volume": 25.338,
  "weight": null,
  "general_product_information": {
    "newegg_sku": "2AM-05GF-00013"
  }
}