{
  "opendb_id": "559dd16f-e58d-4214-bc52-df59fd890ded",
  "memory": {
    "max": 256,
    "ram_type": "DDR5",
    "slots": 4
  },
  "storage_devices": {
    "sata_6_gb_s": 4,
    "sata_3_gb_s": 0,
    "u2": 0
  },
  "usb_headers": {
    "usb_2_0": 3,
    "usb_3_2_gen_1": 1,
    "usb_3_2_gen_2": 0,
    "usb_3_2_gen_2x2": 1,
    "usb_4": 0,
    "usb_4_80g": 0
  },
  "fan_headers": {
    "cpu_fan": 1,
    "case_fan": 5,
    "pump": 1,
    "cpu_opt": 1
  },
  "rgb_headers": {
    "argb_5v": 3,
    "rgb_12v": 0
  },
  "front_panel_headers": {
    "power_button": true,
    "reset_button": true,
    "power_led": true,
    "hdd_led": true
  },
  "other_headers": {
    "thunderbolt": 0,
    "com_port": 1,
    "temperature_sensor": 1
  },
  "power_connectors": {
    "cpu_power": ["8-pin", "8-pin"],
    "main_power": "24-pin"
  },
  "bios_features": {
    "flashback": true,
    "clear_cmos": true
  },
  "audio": {
    "chipset": "Realtek ALC1220P",
    "channels": "7.1"
  },
  "metadata": {
    "name": "Asus X870E ProArt CREATOR WIFI AM5 DDR5 ATX",
    "manufacturer": "ASUS",
    "part_numbers": ["ProArt X870E-CREATOR WIFI", "90mb1ig0-m0aay0", "90MB1IG0-M0EAY0"],
    "variant": "X870E-CREATOR WIFI",
    "series": "ProArt",
    "manufacturer_color": "Black",
    "releaseYear": 2024
  },
  "socket": "AM5",
  "form_factor": "ATX",
  "chipset": "AMD X870E",
  "color": ["BLACK", "GOLD"],
  "pcie_slots": [
    {
      "gen": "5.0",
      "quantity": 2,
      "lanes": 16
    },
    {
      "gen": "4.0",
      "quantity": 1,
      "lanes": 4
    }
  ],
  "m2_slots": [
    {
      "size": "2242/2260/2280",
      "key": "M",
      "interface": "PCIe 5.0 x4"
    },
    {
      "size": "2242/2260/2280",
      "key": "M",
      "interface": "PCIe 5.0 x4"
    },
    {
      "size": "2242/2260/2280",
      "key": "M",
      "interface": "PCIe 4.0 x4"
    },
    {
      "size": "2242/2260/2280/22110",
      "key": "M",
      "interface": "PCIe 4.0 x4"
    }
  ],
  "onboard_ethernet": [
    {
      "speed": "10 Gb/s",
      "controller": "Marvell AQtion"
    }
  ],
  "ecc_support": true,
  "raid_support": true,
  "back_connect_connectors": false,
  "back_panel_ports": [
    "2 x USB4® (40Gbps) port(s) (2 x USB Type-C®)",
    "1 x USB 20Gbps port (1 x USB Type-C®)",
    "7 x USB 10Gbps ports (7 x Type-A)",
    "1 x USB 2.0 port (1 x Type-A)",
    "1 x DisplayPort (Input only)",
    "1 x HDMITM port",
    "1 x Wi-Fi Module",
    "1 x Marvell® AQtion 10Gb Ethernet",
    "1 x Intel® 2.5Gb Ethernet",
    "3 x Audio jacks",
    "1 x BIOS FlashBack™ button",
    "1 x Clear CMOS button"
  ],
  "wireless_networking": "Wifi 7",
  "lighting": ["ARGB"],
  "general_product_information": {
    "amazon_sku": "B0DF123GCV",
    "newegg_sku": "N82E16813119688",
    "walmart_sku": 12688816212,
    "ibuypower_sku": "29936",
    "manufacturer_url": "https://www.asus.com/ph/motherboards-components/motherboards/proart/proart-x870e-creator-wifi/techspec/"
  }
}
