{
  "opendb_id": "43c78ab3-7bbb-4678-a1f0-da334cf6457e",
  "modules": {
    "quantity": 2,
    "capacity_gb": 16
  },
  "metadata": {
    "name": "Corsair Vengeance RGB Pro 32GB (2x16GB) DDR4-3466 CL16",
    "manufacturer": "Corsair",
    "part_numbers": [
      "CMW32GX4M2C3466C16W"
    ],
    "series": "Vengeance",
    "variant": "3466 CL16"
  },
  "speed": 3466,
  "ram_type": "DDR4",
  "form_factor": "288-pin DIMM (DDR4)",
  "capacity": 32,
  "color": [
    "WHITE"
  ],
  "cas_latency": 16,
  "timings": "16-18-18-36",
  "voltage": null,
  "ecc": "Non-ECC",
  "registered": "Unbuffered",
  "heat_spreader": true,
  "rgb": false,
  "general_product_information": {}
}