{
  "opendb_id": "6014008e-517c-44a4-94c4-cabdfc3a5d5f",
  "modules": {
    "quantity": 3,
    "capacity_gb": 2
  },
  "metadata": {
    "name": "PNY XLR8 6 GB (3 x 2 GB) DDR3-1600 CL8",
    "manufacturer": "PNY",
    "part_numbers": [
      "MD6144KD3-1600-X8"
    ],
    "series": "XLR8",
    "variant": "1600 CL8"
  },
  "speed": 1600,
  "ram_type": "DDR3",
  "form_factor": "240-pin DIMM (DDR3)",
  "capacity": 6,
  "color": "Black / Silver",
  "cas_latency": 8,
  "voltage": null,
  "ecc": "Non-ECC",
  "registered": "Unbuffered",
  "heat_spreader": true,
  "rgb": false,
  "general_product_information": {}
}