{
  "opendb_id": "775f5adb-2779-4af1-9de4-69fc5da16950",
  "modules": {
    "quantity": 2,
    "capacity_gb": 16
  },
  "metadata": {
    "name": "Kingston FURY Renegade 32GB (2x16GB) DDR5-6000 CL32",
    "manufacturer": "Kingston",
    "part_numbers": [
      "KF560C32RSK2-32"
    ],
    "series": "FURY",
    "variant": "6000 CL32"
  },
  "speed": 6000,
  "ram_type": "DDR5",
  "form_factor": "288-pin DIMM (DDR5)",
  "capacity": 32,
  "color": [
    "GREY",
    "BLACK"
  ],
  "cas_latency": 32,
  "voltage": null,
  "ecc": "Non-ECC",
  "registered": "Unbuffered",
  "heat_spreader": true,
  "rgb": false,
  "general_product_information": {
    "walmart_sku": 1564694533
  }
}