{
  "opendb_id": "b38d3091-a543-436a-9b30-ed19a69b56c0",
  "modules": {
    "quantity": 2,
    "capacity_gb": 16
  },
  "metadata": {
    "name": "GOODRAM IRDM PRO 32 GB (2 x 16 GB) DDR4-3600 CL18",
    "manufacturer": "GOODRAM",
    "part_numbers": [
      "IRP-K3600D4V64L18",
      "32GDC"
    ],
    "series": "IRDM",
    "variant": "3600 CL18"
  },
  "speed": 3600,
  "ram_type": "DDR4",
  "form_factor": "288-pin DIMM (DDR4)",
  "capacity": 32,
  "color": "Black",
  "cas_latency": 18,
  "voltage": null,
  "ecc": "Non-ECC",
  "registered": "Unbuffered",
  "heat_spreader": true,
  "rgb": false,
  "general_product_information": {}
}