{
  "opendb_id": "deaa8f29-7c32-4a18-abdd-2b0710990ec0",
  "modules": {
    "quantity": 4,
    "capacity_gb": 16
  },
  "metadata": {
    "name": "G.Skill Ripjaws V 64 GB (4 x 16 GB) DDR4-3200 CL14",
    "manufacturer": "G.Skill",
    "part_numbers": [
      "F4-3200C14Q-64GVK"
    ],
    "series": "Ripjaws",
    "variant": "3200 CL14"
  },
  "speed": 3200,
  "ram_type": "DDR4",
  "form_factor": "288-pin DIMM (DDR4)",
  "capacity": 64,
  "color": "Black",
  "cas_latency": 14,
  "voltage": null,
  "ecc": "Non-ECC",
  "registered": "Unbuffered",
  "heat_spreader": true,
  "rgb": false,
  "general_product_information": {}
}