{
  "opendb_id": "7a9c7440-6aca-4f8e-a6a1-9ae438789cd9",
  "cores": {
    "total": 4,
    "performance": 0,
    "threads": 8,
    "efficiency": 0
  },
  "clocks": {
    "performance": {
      "base": 3.6,
      "boost": 3.9
    },
    "efficiency": {
      "base": 0,
      "boost": 0
    }
  },
  "cache": {
    "l2": 2,
    "l3": 16,
    "l1": "32 KB L1 Data + 32 KB L1 Instruction per core (64 KB per core, 256 KB total across 4 cores)"
  },
  "specifications": {
    "integratedGraphics": {
      "model": "None",
      "baseClock": 0,
      "boostClock": 0,
      "shaderCount": 0
    },
    "memory": {
      "maxSupport": 128,
      "types": ["DDR4"],
      "channels": 2
    },
    "tdp": 65,
    "eccSupport": false,
    "includesCooler": true,
    "packaging": "Boxed",
    "lithography": "TSMC 7nm FinFET",
    "simultaneousMultithreading": true,
    "ppt": 88
  },
  "metadata": {
    "name": "AMD Ryzen 3 3100",
    "manufacturer": "AMD",
    "part_numbers": ["100-100000284BOX"],
    "series": "Ryzen 3 3000",
    "variant": "3100",
    "releaseYear": 2020
  },
  "series": "Ryzen 3 3000",
  "microarchitecture": "Zen 2",
  "coreFamily": "Matisse",
  "socket": "AM4",
  "general_product_information": {
    "amazon_sku": "B0876Y2TMZ",
    "newegg_sku": "N82E16819113649",
    "bestbuy_sku": 6423072,
    "walmart_sku": 480277736,
    "manufacturer_url": "https://www.amd.com/en/support/downloads/drivers.html/processors/ryzen/ryzen-3000-series/amd-ryzen-3-3100.html"
  }
}
