{
  "opendb_id": "0253b438-29b6-4274-b0e1-08ec3cf307c3",
  "metadata": {
    "name": "Thermaltake Riing Trio 12 RGB TT Premium Edition 41.13 CFM 120 mm Fans 3-Pack",
    "manufacturer": "Thermaltake",
    "series": "Riing",
    "variant": "120mm Black"
  },
  "size": 120,
  "color": "Black",
  "quantity": 3,
  "min_airflow": 41.13,
  "max_airflow": null,
  "min_noise_level": 25.2,
  "max_noise_level": null,
  "pwm": true,
  "led": "RGB",
  "connector": "Proprietary PWM",
  "controller": "USB",
  "static_pressure": 1.4,
  "flow_direction": "Standard",
  "general_product_information": {
    "newegg_sku": "9SIA8EF84H8921",
    "bestbuy_sku": 6353129,
    "walmart_sku": 636299962
  }
}