{
  "opendb_id": "15951085-76ad-4547-a6e3-b406d538e715",
  "metadata": {
    "name": "be quiet! Light Wings PWM 41.51 CFM 120mm",
    "manufacturer": "be quiet!",
    "series": "Light",
    "variant": "120mm Black"
  },
  "size": 120,
  "color": [
    "BLACK"
  ],
  "quantity": 1,
  "min_airflow": 41.51,
  "max_airflow": null,
  "min_noise_level": 20.6,
  "max_noise_level": null,
  "pwm": true,
  "led": "Addressable RGB",
  "connector": "4-pin PWM + 3-pin 5V Addressable RGB",
  "controller": "None",
  "static_pressure": 1.66,
  "flow_direction": "Standard",
  "general_product_information": {}
}