{
  "opendb_id": "18f1b1f9-9de2-44d9-bb20-a9d59cebe223",
  "metadata": {
    "name": "Azza Hurricane 120mm 56.12 CFM",
    "manufacturer": "Azza",
    "series": "Hurricane",
    "variant": "120mm Black / White"
  },
  "size": 120,
  "color": [
    "BLACK",
    "WHITE"
  ],
  "quantity": 1,
  "min_airflow": 56.12,
  "max_airflow": null,
  "min_noise_level": 29.8,
  "max_noise_level": null,
  "pwm": true,
  "led": "RGB",
  "connector": "4-pin PWM + 4-pin 12V RGB",
  "controller": "None",
  "static_pressure": 1.79,
  "flow_direction": "Standard",
  "general_product_information": {}
}