{
  "opendb_id": "21cbc38e-0bf7-4e95-8ef7-48dc70f25686",
  "metadata": {
    "name": "ID-COOLING NO-9225-SD 92mm 28.5 CFM",
    "manufacturer": "ID-COOLING",
    "series": "NO-9225-SD",
    "variant": "92mm Black"
  },
  "size": 92,
  "color": [
    "BLACK"
  ],
  "quantity": 1,
  "min_airflow": 28.5,
  "max_airflow": null,
  "min_noise_level": 20,
  "max_noise_level": null,
  "pwm": false,
  "led": "None",
  "connector": "3-pin",
  "controller": "None",
  "static_pressure": null,
  "flow_direction": "Standard",
  "general_product_information": {}
}