{
  "opendb_id": "4a63e07c-8ceb-4808-97d8-fcec25ac9150",
  "metadata": {
    "name": "BitFenix Spectre Black 120mm",
    "manufacturer": "BitFenix",
    "series": "Spectre",
    "variant": "120mm Black"
  },
  "size": 120,
  "color": [
    "BLACK"
  ],
  "quantity": 1,
  "min_airflow": 43.5,
  "max_airflow": null,
  "min_noise_level": 20,
  "max_noise_level": null,
  "pwm": false,
  "led": "Blue",
  "connector": "3-pin",
  "controller": "None",
  "static_pressure": 0.62,
  "flow_direction": "Standard",
  "general_product_information": {}
}