{
  "opendb_id": "5bf99ac7-2962-4cd1-8707-5249c7427931",
  "metadata": {
    "name": "Aerocool Silent Master 76 CFM 200 mm Fan",
    "manufacturer": "Aerocool",
    "series": "Silent",
    "variant": "200mm Red"
  },
  "size": 200,
  "color": "Red",
  "quantity": 1,
  "min_airflow": 76,
  "max_airflow": null,
  "min_noise_level": 18,
  "max_noise_level": null,
  "pwm": false,
  "led": "Red",
  "connector": "3-pin",
  "controller": "None",
  "static_pressure": 0.36,
  "flow_direction": "Standard",
  "general_product_information": {}
}