{
  "opendb_id": "661621e7-a66d-4b8a-99dc-ebab987f7cc2",
  "metadata": {
    "name": "Apevia C 57.67 CFM 120 mm Fans 3-Pack",
    "manufacturer": "Apevia",
    "series": "C",
    "variant": "120mm Black / White"
  },
  "size": 120,
  "color": "Black / White",
  "quantity": 3,
  "min_airflow": 57.67,
  "max_airflow": null,
  "min_noise_level": 24.7,
  "max_noise_level": null,
  "pwm": false,
  "led": "White",
  "connector": "3-pin",
  "controller": "None",
  "static_pressure": 0.96,
  "flow_direction": "Standard",
  "general_product_information": {
    "newegg_sku": "9SIB698K3T1230"
  }
}