{
  "opendb_id": "691e5d24-e36f-4a11-9b1d-3a1cff4eea41",
  "metadata": {
    "name": "Enermax T.B. Vegas Single 75.98 CFM 120 mm Fan",
    "manufacturer": "Enermax",
    "series": "T.B.",
    "variant": "120mm Blue"
  },
  "size": 120,
  "color": "Blue",
  "quantity": 1,
  "min_airflow": 20.42,
  "max_airflow": 75.98,
  "min_noise_level": 14,
  "max_noise_level": 25,
  "pwm": true,
  "led": "Blue",
  "connector": "4-pin PWM",
  "controller": "None",
  "static_pressure": null,
  "flow_direction": "Standard",
  "general_product_information": {}
}