{
  "opendb_id": "785b2cd4-0d1d-4a74-9b80-f20344ffb08c",
  "metadata": {
    "name": "Corsair AF120 52.19 CFM 120 mm Fan",
    "manufacturer": "Corsair",
    "series": "AF120",
    "variant": "120mm Purple"
  },
  "size": 120,
  "color": "Purple",
  "quantity": 1,
  "min_airflow": 52.19,
  "max_airflow": null,
  "min_noise_level": 25.2,
  "max_noise_level": null,
  "pwm": false,
  "led": "Purple",
  "connector": "3-pin",
  "controller": "None",
  "static_pressure": null,
  "flow_direction": "Standard",
  "general_product_information": {}
}