{
  "opendb_id": "7ffa16b5-10f2-4e28-b4c2-e3802601b72f",
  "metadata": {
    "name": "Lian Li UNI FAN P28 92 CFM 120 mm",
    "manufacturer": "Lian Li",
    "series": "UNI",
    "variant": "120mm White"
  },
  "size": 120,
  "color": [],
  "quantity": 1,
  "min_airflow": 44.94,
  "max_airflow": 92,
  "min_noise_level": 20.4,
  "max_noise_level": 32.1,
  "pwm": true,
  "led": "None",
  "connector": "4-pin PWM",
  "controller": "None",
  "static_pressure": 4.79,
  "flow_direction": "Standard",
  "general_product_information": {
    "walmart_sku": 1363557357
  }
}