{
  "opendb_id": "84f36660-3693-4bdb-97c3-bc9e554a332e",
  "metadata": {
    "name": "Corsair SP120 Quiet 120mm 37.85 CFM",
    "manufacturer": "Corsair",
    "series": "SP120",
    "variant": "120mm Black"
  },
  "size": 120,
  "color": [
    "BLACK"
  ],
  "quantity": 1,
  "min_airflow": 37.85,
  "max_airflow": null,
  "min_noise_level": 23,
  "max_noise_level": null,
  "pwm": true,
  "led": "None",
  "connector": "4-pin PWM",
  "controller": "None",
  "static_pressure": 3.1,
  "flow_direction": "Standard",
  "general_product_information": {}
}