{
  "opendb_id": "87570c17-97ee-4518-bb7a-3d99501f7d98",
  "metadata": {
    "name": "NoiseBlocker BlackSilentFan X-2 57.68 CFM 120 mm Fan",
    "manufacturer": "NoiseBlocker",
    "series": "BlackSilentFan",
    "variant": "120mm Translucent Blue"
  },
  "size": 120,
  "color": "Blue",
  "quantity": 1,
  "min_airflow": 57.68,
  "max_airflow": null,
  "min_noise_level": 24,
  "max_noise_level": null,
  "pwm": false,
  "led": "None",
  "connector": "3-pin",
  "controller": "None",
  "static_pressure": null,
  "flow_direction": "Standard",
  "general_product_information": {}
}