{
  "opendb_id": "8fb73860-8a6f-4484-ac7f-d538792dd6ab",
  "metadata": {
    "name": "Prolimatech Vortex 72.67 CFM 120 mm Fan",
    "manufacturer": "Prolimatech",
    "series": "Vortex",
    "variant": "120mm Blue"
  },
  "size": 120,
  "color": "Blue",
  "quantity": 1,
  "min_airflow": 72.67,
  "max_airflow": null,
  "min_noise_level": 29.1,
  "max_noise_level": null,
  "pwm": false,
  "led": "None",
  "connector": "3-pin",
  "controller": "None",
  "static_pressure": null,
  "flow_direction": "Standard",
  "general_product_information": {}
}