{
  "opendb_id": "923b0c6f-b8b8-4da8-a5e4-247524434f45",
  "metadata": {
    "name": "Phanteks M25-120 PWM 120mm Fans 3-Pack",
    "manufacturer": "Phanteks",
    "series": "M25-120",
    "variant": "120mm Black"
  },
  "size": 120,
  "color": [
    "BLACK"
  ],
  "quantity": 3,
  "min_airflow": 84.26,
  "max_airflow": null,
  "min_noise_level": 35.7,
  "max_noise_level": null,
  "pwm": true,
  "led": "None",
  "connector": "4-pin PWM",
  "controller": "None",
  "static_pressure": 2.67,
  "flow_direction": "Standard",
  "general_product_information": {
    "newegg_sku": "N82E16835709210",
    "walmart_sku": 3988880450
  }
}