{
  "opendb_id": "a76d02ba-44e8-4bee-b26c-2345b7f87f99",
  "metadata": {
    "name": "Corsair iCUE SP140 RGB ELITE 68.1 CFM 140 mm Fan",
    "manufacturer": "Corsair",
    "series": "iCUE",
    "variant": "140mm Black / White"
  },
  "size": 140,
  "color": "Black / White",
  "quantity": 1,
  "min_airflow": null,
  "max_airflow": null,
  "min_noise_level": null,
  "max_noise_level": null,
  "pwm": true,
  "led": "Addressable RGB",
  "connector": "4-pin PWM + Proprietary RGB",
  "controller": "None",
  "static_pressure": 1.66,
  "flow_direction": "Standard",
  "general_product_information": {}
}