{
  "opendb_id": "aade74fe-2257-47d0-bb4f-66a911995982",
  "metadata": {
    "name": "Noctua S12A PWM 120 mm Fan",
    "manufacturer": "Noctua",
    "series": "S12A",
    "variant": "120mm Brown"
  },
  "size": 120,
  "color": "Brown",
  "quantity": 1,
  "min_airflow": null,
  "max_airflow": null,
  "min_noise_level": 10.7,
  "max_noise_level": 17.8,
  "pwm": true,
  "led": "None",
  "connector": "4-pin PWM",
  "controller": "None",
  "static_pressure": null,
  "flow_direction": "Standard",
  "general_product_information": {
    "newegg_sku": "N82E16835608038"
  }
}