{
  "opendb_id": "b4a108d6-bfc7-4583-a05a-2680c4dac91a",
  "metadata": {
    "name": "Silverstone Shark Force 120 CFM 140 mm Fan",
    "manufacturer": "Silverstone",
    "series": "Shark",
    "variant": "140mm Black"
  },
  "size": 140,
  "color": "Black",
  "quantity": 1,
  "min_airflow": 0,
  "max_airflow": 120,
  "min_noise_level": 0,
  "max_noise_level": 38.3,
  "pwm": true,
  "led": "Addressable RGB",
  "connector": "4-pin PWM + 3-pin 5V Addressable RGB",
  "controller": "None",
  "static_pressure": 4,
  "flow_direction": "Standard",
  "general_product_information": {}
}