{
  "opendb_id": "c36c36d5-3df5-4548-89ae-c648c73b5ad2",
  "metadata": {
    "name": "be quiet! Light Wings PWM 56 CFM 140mm Fans 3-Pack",
    "manufacturer": "be quiet!",
    "series": "Light",
    "variant": "140mm Black"
  },
  "size": 140,
  "color": [
    "BLACK"
  ],
  "quantity": 3,
  "min_airflow": 56,
  "max_airflow": null,
  "min_noise_level": 23.3,
  "max_noise_level": null,
  "pwm": true,
  "led": "Addressable RGB",
  "connector": "4-pin PWM + 3-pin 5V Addressable RGB",
  "controller": "5V Addressable RGB",
  "static_pressure": 1.49,
  "flow_direction": "Standard",
  "general_product_information": {}
}