{
  "opendb_id": "d0fea033-8f27-4291-89c6-69177f9914d7",
  "metadata": {
    "name": "Vantec Tornado 119 CFM 92 mm Fan",
    "manufacturer": "Vantec",
    "series": "Tornado",
    "variant": "92mm Black"
  },
  "size": 92,
  "color": "Black",
  "quantity": 1,
  "min_airflow": 119,
  "max_airflow": null,
  "min_noise_level": 56.4,
  "max_noise_level": null,
  "pwm": false,
  "led": "None",
  "connector": "3-pin",
  "controller": "None",
  "static_pressure": null,
  "flow_direction": "Standard",
  "general_product_information": {}
}