{
  "opendb_id": "e0904109-b1ad-4d8a-82ca-17b4cbfd20b0",
  "metadata": {
    "name": "GAMDIAS AEOLus M1 45.2 CFM 120 mm Fan",
    "manufacturer": "GAMDIAS",
    "series": "AEOLus",
    "variant": "120mm Black"
  },
  "size": 120,
  "color": "Black",
  "quantity": 1,
  "min_airflow": 45.2,
  "max_airflow": null,
  "min_noise_level": 31,
  "max_noise_level": null,
  "pwm": false,
  "led": "RGB",
  "connector": "3-pin + Proprietary RGB",
  "controller": "Manual",
  "static_pressure": 1.05,
  "flow_direction": "Standard",
  "general_product_information": {}
}