{
  "opendb_id": "ebd452db-9cf6-428e-a9c7-b0ffbced5d3e",
  "metadata": {
    "name": "HYTE FA12 Fans 4-Pack Wild Cherry",
    "manufacturer": "HYTE",
    "series": "Flow FA12",
    "variant": "Wild Cherry",
    "part_numbers": []
  },
  "size": 120,
  "color": [
    "RED"
  ],
  "quantity": 4,
  "max_airflow": 72,
  "max_noise_level": 28,
  "pwm": true,
  "led": "None",
  "static_pressure": 1.6,
  "flow_direction": "Standard",
  "isOEM": false,
  "general_product_information": {
    "hyte_sku": "31846",
    "manufacturer_url": "https://hyte.com/store/flow-fa12-fan-4-pack/fan-hyte-fa12-rr-4"
  }
}