{
  "opendb_id": "f4a68174-f732-46a6-9fa9-495fbdbfdd98",
  "metadata": {
    "name": "Akasa Viper 83.63 CFM 120 mm",
    "manufacturer": "Akasa",
    "series": "Viper",
    "variant": "120mm Black / Yellow"
  },
  "size": 120,
  "color": [
    "BLACK",
    "YELLOW"
  ],
  "quantity": 1,
  "min_airflow": 83.63,
  "max_airflow": null,
  "min_noise_level": 6.9,
  "max_noise_level": 28.9,
  "pwm": true,
  "led": "None",
  "connector": "4-pin PWM",
  "controller": "None",
  "static_pressure": 2.98,
  "flow_direction": "Standard",
  "general_product_information": {}
}