{
  "opendb_id": "2b8dc58f-473d-43b2-a142-9c05eb98399f",
  "metadata": {
    "name": "KOLINK Umbra EX180 Black Edition 73.6 CFM",
    "manufacturer": "KOLINK",
    "part_numbers": [
      "PGW-CC-KOL-002                                                    UMBRA-EX180-BLACK-EDITION"
    ],
    "series": "Umbra",
    "variant": "Black",
    "releaseYear": null
  },
  "min_fan_rpm": 800,
  "max_fan_rpm": 1800,
  "min_noise_level": 28.6,
  "max_noise_level": null,
  "color": "Black",
  "height": 157,
  "cpu_sockets": [
    "AM4",
    "AM5",
    "LGA1150",
    "LGA1151",
    "LGA1155",
    "LGA1156",
    "LGA1200",
    "LGA1700",
    "LGA1851"
  ],
  "water_cooled": false,
  "radiator_size": null,
  "fanless": false,
  "fan_size": null,
  "fan_quantity": null,
  "general_product_information": {}
}