{
  "opendb_id": "d972e853-85fb-47d0-9d23-10ab2c5b28df",
  "metadata": {
    "name": "Inter-Tech ALSEYE W90 55.65 CFM",
    "manufacturer": "Inter-Tech",
    "part_numbers": [
      "W90"
    ],
    "series": "ALSEYE",
    "variant": "White / Black",
    "releaseYear": null
  },
  "min_fan_rpm": 3000,
  "max_fan_rpm": null,
  "min_noise_level": 36.7,
  "max_noise_level": null,
  "color": "White / Black",
  "height": 82,
  "cpu_sockets": [
    "LGA1150",
    "LGA1151",
    "LGA1155",
    "LGA1156",
    "LGA1200",
    "LGA1700",
    "LGA1851"
  ],
  "water_cooled": false,
  "radiator_size": null,
  "fanless": false,
  "fan_size": null,
  "fan_quantity": null,
  "general_product_information": {}
}