{
  "opendb_id": "15fc192d-aabc-47ad-a055-67406c109f06",
  "metadata": {
    "name": "KOORUI 1500R 27-inch FHD 180Hz Monitor Curved, Adaptive Sync",
    "manufacturer": "KOORUI",
    "series": "1500R"
  },
  "general_product_information": {
    "amazon_sku": "B0D547L48X"
  },
  "screen_size": 27,
  "resolution": {
    "horizontalRes": 1920,
    "verticalRes": 1080
  },
  "refresh_rate": 180,
  "aspect_ratio": "16:9",
  "connectors": "HDMI, DisplayPort",
  "adaptive_sync": "VESA Adaptive-Sync"
}
