{
  "opendb_id": "17c35d33-96fe-4ced-b8eb-2085d7a4b583",
  "resolution": {
    "horizontalRes": 2560,
    "verticalRes": 1440
  },
  "metadata": {
    "name": "Samsung 27-inch Odyssey OLED G6 G60SF QHD 500Hz Gaming Monitor",
    "manufacturer": "Samsung",
    "part_numbers": ["8285f8c77e54ce1a", "G60SF", "LS27FG602SNXZA"]
  },
  "screen_size": 27,
  "refresh_rate": 500,
  "panel_type": "QD-OLED",
  "color": [],
  "lighting": [],
  "general_product_information": {
    "amazon_sku": "B0FJYRV9TK",
    "newegg_sku": "N82E16824027372R",
    "bestbuy_sku": 6635360,
    "walmart_sku": 17824308812
  }
}
