{
  "opendb_id": "2250d64b-fc85-49b1-9915-7fdb4c360087",
  "resolution": {
    "horizontalRes": 2560,
    "verticalRes": 1440
  },
  "metadata": {
    "name": "Asus ROG Swift PG27VQ 27.0\" 2560 x 1440 165 Hz Curved",
    "manufacturer": "Asus",
    "part_numbers": [
      "PG27VQ                                                    90LM03N3-B01370"
    ],
    "series": "",
    "variant": "",
    "model": "ROG Swift PG27VQ"
  },
  "screen_size": 27,
  "refresh_rate": 165,
  "panel_type": "TN",
  "response_time": 1,
  "color": [],
  "viewing_angle": "170° H x 160° V",
  "aspect_ratio": "16:9",
  "connectors": "1 x HDMI                                                    1 x DisplayPort",
  "max_brightness": "400 cd/m²",
  "hdr": "",
  "adaptive_sync": "G-Sync",
  "general_product_information": {}
}