{
  "opendb_id": "30725288-7e4d-4244-b0f4-24a956996b33",
  "resolution": {
    "horizontalRes": 3440,
    "verticalRes": 1440
  },
  "metadata": {
    "name": "LG 34CB99-W 34.0\" 3440 x 1440 60 Hz Curved",
    "manufacturer": "LG",
    "part_numbers": [
      "34CB99-W"
    ],
    "series": "34CB99-W",
    "variant": "White",
    "model": "34CB99-W"
  },
  "screen_size": 34,
  "refresh_rate": 60,
  "panel_type": "IPS",
  "response_time": 5,
  "color": [
    "WHITE"
  ],
  "viewing_angle": "178° H x 178° V",
  "aspect_ratio": "21:9",
  "connectors": "2 x HDMI                                                    1 x DisplayPort",
  "max_brightness": "30 cd/m²",
  "hdr": "",
  "adaptive_sync": "FreeSync",
  "general_product_information": {}
}