{
  "opendb_id": "4d374cf5-361a-4166-9307-bdb7f76684bb",
  "resolution": {
    "horizontalRes": 1680,
    "verticalRes": 1050
  },
  "metadata": {
    "name": "Asus VW222U 22.0\" 1680 x 1050 75 Hz",
    "manufacturer": "Asus",
    "part_numbers": [
      "VW222U"
    ],
    "series": "",
    "variant": "Black",
    "model": "VW222U"
  },
  "screen_size": 22,
  "refresh_rate": 75,
  "panel_type": "TN",
  "response_time": 2,
  "color": [
    "BLACK"
  ],
  "viewing_angle": "170° H x 160° V",
  "aspect_ratio": "16:10",
  "connectors": "1 x VGA                                                    1 x DVI",
  "max_brightness": "300 cd/m²",
  "hdr": "",
  "adaptive_sync": "None",
  "general_product_information": {}
}