{
  "opendb_id": "94b4f42f-de48-415f-8f9d-a11bcaaf6ef2",
  "resolution": {
    "horizontalRes": 1440,
    "verticalRes": 900
  },
  "metadata": {
    "name": "Dell P1911 19.0\" 1440 x 900",
    "manufacturer": "Dell",
    "part_numbers": [
      "469-0052"
    ],
    "series": "",
    "variant": "",
    "model": "P1911"
  },
  "screen_size": 19,
  "refresh_rate": 0,
  "panel_type": "",
  "response_time": 5,
  "color": [],
  "viewing_angle": "160° H x 160° V",
  "aspect_ratio": "16:10",
  "connectors": "1 x VGA                                                    1 x DVI",
  "max_brightness": "250 cd/m²",
  "hdr": "",
  "adaptive_sync": "None",
  "general_product_information": {}
}