{
  "opendb_id": "9d3869ff-3034-4992-b88e-c96c564ca00f",
  "resolution": {
    "horizontalRes": 1440,
    "verticalRes": 900
  },
  "metadata": {
    "name": "Acer B193WGJbmdh 19.0\" 1440 x 900",
    "manufacturer": "Acer",
    "part_numbers": [
      "ET.CB3WP.G01"
    ],
    "series": "",
    "variant": "",
    "model": "B193WGJbmdh"
  },
  "screen_size": 19,
  "refresh_rate": 0,
  "panel_type": "",
  "response_time": 5,
  "color": [],
  "viewing_angle": "160° H x 160° V",
  "aspect_ratio": "16:10",
  "connectors": "1 x VGA                                                    1 x DVI",
  "max_brightness": "250 cd/m²",
  "hdr": "",
  "adaptive_sync": "None",
  "general_product_information": {}
}