{
  "opendb_id": "f1515887-a20a-4cc8-b721-1ddb19d8185e",
  "resolution": {
    "horizontalRes": 3840,
    "verticalRes": 2160
  },
  "metadata": {
    "name": "ViewSonic VG2860MHL-4K 28.0\" 3840 x 2160 60 Hz",
    "manufacturer": "ViewSonic",
    "part_numbers": [
      "VG2860MHL-4K"
    ],
    "series": "VG2860MHL-4K",
    "variant": "",
    "model": "VG2860MHL-4K"
  },
  "screen_size": 28,
  "refresh_rate": 60,
  "panel_type": "TN",
  "response_time": 2,
  "color": [],
  "viewing_angle": "170° H x 160° V",
  "aspect_ratio": "16:9",
  "connectors": "1 x HDMI                                                    2 x DisplayPort                                                    1 x DVI",
  "max_brightness": "300 cd/m²",
  "hdr": "",
  "adaptive_sync": "None",
  "general_product_information": {}
}