{
  "opendb_id": "283b203a-bf7d-48c3-8834-b32def0ce31f",
  "dimensions": {
    "length": 118.2,
    "width": 61.6,
    "height": 38.3
  },
  "metadata": {
    "name": "EWEADN Z7",
    "manufacturer": "EWEADN",
    "series": "Z7",
    "part_numbers": []
  },
  "weight": 49,
  "size": "Medium",
  "shape": "Ambidextrous",
  "connectivity": ["Wireless 2.4GHz"],
  "sensor": "PixArt PAW3950 Ultra",
  "max_dpi": 42000,
  "polling_rate": 8000,
  "switches": "Omron Optical",
  "grip_types": [],
  "lighting": [],
  "general_product_information": {
    "amazon_sku": "B0GLGK8SNJ"
  }
}
