{
  "opendb_id": "abeb2a27-8c31-49e2-bca1-67cf8719018f",
  "metadata": {
    "name": "Glorious Model D 2 Wired",
    "manufacturer": "Glorious",
    "series": "Model D 2",
    "variant": "Wired"
  },
  "weight": 58,
  "dimensions": {
    "length": 127,
    "width": 67,
    "height": 43
  },
  "size": "Large",
  "shape": "Ergonomic",
  "connectivity": ["Wired"],
  "sensor": "Glorious BAMF 2.0",
  "max_dpi": 26000,
  "polling_rate": 1000,
  "switches": "Glorious Mouse Switches",
  "general_product_information": {
    "amazon_sku": "B0D38B66W3"
  }
}
