{
  "opendb_id": "196d80c7-feda-482e-9fe5-dfc5646a8727",
  "metadata": {
    "name": "Keychron K5 SE Bluetooth/Wired Slim Keychron Optical Red Low Profile Keyboard",
    "manufacturer": "Keychron",
    "part_numbers": ["K5SED1", "Keychron K5 SE"],
    "releaseYear": 2022
  },
  "connectivity": ["Bluetooth", "Wired USB-C"],
  "features": ["Low Profile"],
  "general_product_information": {},
  "battery_capacity": 2000,
  "size": "Full Size",
  "backlighting": "RGB",
  "frame_material": "Aluminum Plastic",
  "switch_type": "Clicky",
  "keycap_material": "ABS",
  "switch": "Keychron Optical",
  "hot_swappable": true
}
