{
  "opendb_id": "43d7ab6c-45a8-4021-90c8-3dd9bc0fa5ab",
  "metadata": {
    "name": "Logitech Alto Keys K98M Wireless Mechanical Keyboard, Customizable Keyboard with Vibration Absorbing Gasket, Backlit Keys, Bluetooth, USB-C Charging, for PC, Mac, Laptops - Lilac",
    "manufacturer": "Logitech",
    "series": "Alto Keys K98M"
  },
  "general_product_information": {
    "amazon_sku": "B0FMCJ1NJZ"
  },
  "connectivity": [
    "Bluetooth",
    "Wireless 2.4GHz",
    "Wired USB-C"
  ],
  "backlighting": "Single Color"
}
