{
  "opendb_id": "c6727985-03e5-4972-a742-fcb726393923",
  "metadata": {
    "name": "SEUNKWANG EWEADN Typewriter Style Mechanical Keyboard, Wired Typewriter Keyboard,104 Keys Retro Typewriter Keyboards, Media Control Knob, Wired Computer Keyboard White Switch for Windows/PC-White",
    "manufacturer": "SEUNKWANG",
    "part_numbers": ["V20"]
  },
  "switch": "White",
  "switch_type": "Linear",
  "size": "Full Size",
  "backlighting": "Single Color",
  "connectivity": ["Wired USB-A"],
  "features": [],
  "lighting": [],
  "general_product_information": {
    "amazon_sku": "B0DFY9R641"
  }
}
