{
  "opendb_id": "cfee4c69-6714-44ae-baa4-742789b28142",
  "metadata": {
    "name": "EPOMAKER X Aula F75 MAX Wireless Mechanical Keyboard with TFT Screen and Knob, Gasket Gaming Keyboard in 75% Layout, Hot Swappable, RGB Backlight, for PC/Mac/Linux (Blue&White&Purple)",
    "manufacturer": "EPOMAKER",
    "series": "F75 MAX"
  },
  "general_product_information": {
    "amazon_sku": "B0DPX16QCK"
  },
  "connectivity": ["Wireless 2.4GHz"],
  "features": ["Knob", "Screen"],
  "backlighting": "RGB",
  "hot_swappable": true
}
