{
  "opendb_id": "2b175557-ed89-48fa-b8f0-1f0b1d57dea4",
  "metadata": {
    "name": "TONGVEO All-in-One Conference Room Video Camera System Al Auto-Tracking HD1080P 60fps 3X Optical Zoom USB3.0 HDMI PTZ Camera and Bluetooth Conference Speakerphone with Microphones",
    "manufacturer": "TONGVEO",
    "part_numbers": ["HD1080P"],
    "series": "HD1080P",
    "variant": "3x Zoom"
  },
  "frame_rate": "60fps",
  "connectivity_type": ["Bluetooth", "Wired"],
  "general_product_information": {
    "amazon_sku": "B0B5R6KD2H"
  }
}
